nonebot_plugin_wordle_simple/AnswerDictionary.txt
nonebot_plugin_wordle_simple/GuessDictionary.txt
nonebot_plugin_wordle_simple/__init__.py
nonebot_plugin_wordle_simple/config.py
nonebot_plugin_wordle_simple/fonts/FiraCode-Medium.ttf
nonebot_plugin_wordle_simple/get_translate.py
nonebot_plugin_wordle_simple/img.py
nonebot_plugin_wordle_simple-0.0.7.dist-info/METADATA
nonebot_plugin_wordle_simple-0.0.7.dist-info/WHEEL
nonebot_plugin_wordle_simple-0.0.7.dist-info/licenses/LICENSE
nonebot_plugin_wordle_simple-0.0.7.dist-info/RECORD
