Metadata-Version: 2.4
Name: nonebot-plugin-wordle-simple
Version: 0.0.7
Summary: 一个简单的没有次数限制的猜词游戏 (Wordle) 插件
License: MIT
License-File: LICENSE
Author: shiyihang2007
Author-email: 467557146@qq.com
Requires-Python: >=3.10
Classifier: License :: OSI Approved :: MIT License
Classifier: Programming Language :: Python :: 3
Classifier: Programming Language :: Python :: 3.10
Classifier: Programming Language :: Python :: 3.11
Classifier: Programming Language :: Python :: 3.12
Classifier: Programming Language :: Python :: 3.13
Classifier: Programming Language :: Python :: 3.14
Requires-Dist: httpx (>=0.27.0)
Requires-Dist: nonebot-adapter-onebot (>=2.4.4)
Requires-Dist: nonebot2 (>=2.2.0)
Requires-Dist: pillow (>=10.4.0)
Project-URL: Documentation, https://github.com/shiyihang2007/nonebot-plugin-wordle-simple
Project-URL: Homepage, https://github.com/shiyihang2007/nonebot-plugin-wordle-simple
Project-URL: Repository, https://github.com/shiyihang2007/nonebot-plugin-wordle-simple
